busca_py-2.3.1.dist-info/METADATA
busca_py-2.3.1.dist-info/WHEEL
busca_py/__init__.py
busca_py/__init__.pyi
busca_py/py.typed
busca_py/busca_py.cpython-310-darwin.so
busca_py-2.3.1.dist-info/RECORD
