Metadata-Version: 2.1
Name: busca_py
Version: 2.3.1
Classifier: Programming Language :: Rust
Classifier: Programming Language :: Python :: Implementation :: CPython
Classifier: Programming Language :: Python :: Implementation :: PyPy
Summary: Library to search for files with content that most closely match the lines of a reference string
Keywords: file,match,closest
Author-email: Noah Baculi <noahbaculi@gmail.com>
Requires-Python: >=3.7
Project-URL: Homepage, https://github.com/noahbaculi/busca
Project-URL: Bug Reports, https://github.com/noahbaculi/busca/issues
Project-URL: Source, https://github.com/noahbaculi/busca
